[{"class_name": "fire", "bbox": "340 349 436 417", "used": false}, {"class_name": "fire", "bbox": "478 368 600 409", "used": false}, {"class_name": "fire", "bbox": "453 115 501 371", "used": false}, {"class_name": "fire", "bbox": "340 349 436 417", "used": false}, {"class_name": "fire", "bbox": "478 368 600 409", "used": false}, {"class_name": "fire", "bbox": "453 115 501 371", "used": false}, {"class_name": "fire", "bbox": "340 349 436 417", "used": false}, {"class_name": "fire", "bbox": "478 368 600 409", "used": false}, {"class_name": "fire", "bbox": "453 115 501 371", "used": false}]